CS501A10Assignment/__init__.py
CS501A10Assignment/analysis.py
CS501A10Assignment-0.0.7.dist-info/METADATA
CS501A10Assignment-0.0.7.dist-info/WHEEL
CS501A10Assignment-0.0.7.dist-info/top_level.txt
CS501A10Assignment-0.0.7.dist-info/RECORD
