Metadata-Version: 2.1
Name: CS501A10Assignment
Version: 0.0.7
Summary: CS501 Assignment 10 RA
Author: Ryan August
Author-email: <raugust@g.emporia.edu>
Keywords: python,first package
Classifier: Development Status :: 3 - Alpha
Classifier: Intended Audience :: Education
Classifier: Programming Language :: Python :: 2
Classifier: Programming Language :: Python :: 3
Classifier: Operating System :: MacOS :: MacOS X
Classifier: Operating System :: Microsoft :: Windows
